<solution prefix='mbh12_' sentenceNo='26020' solutionSH='0' siftSolutions='y' status='inprogress' displayEncoding='roman' inflectionFormat='SL' version='2.0'>
	<state>1,3,4,5,9,10,11,12,16</state>
<pada selected='y'>
	<padanum>1</padanum>
	<headword>putra</headword>
	<stem>putra</stem>
	<morphids>mvs</morphids>
	<lexids></lexids>
	<root></root>
	<comment></comment>
</pada>
<pada selected='y'>
	<padanum>2</padanum>
	<headword>kim</headword>
	<stem>ka_1</stem>
	<morphids>n1s</morphids>
	<lexids></lexids>
	<root></root>
	<comment></comment>
</pada>
<pada selected='y'>
	<padanum>3</padanum>
	<headword>para</headword>
	<stem>para</stem>
	<morphids>iic</morphids>
	<lexids></lexids>
	<root></root>
	<comment></comment>
</pada>
<pada>
	<padanum>4</padanum>
	<headword>pakza</headword>
	<stem>pakza</stem>
	<morphids>iic</morphids>
	<lexids>ck</lexids>
	<root></root>
	<comment></comment>
</pada>
<pada>
	<padanum>7</padanum>
	<headword>varDanaH</headword>
	<stem>varDana</stem>
	<morphids>m1s</morphids>
	<lexids>ctp6</lexids>
	<root></root>
	<comment></comment>
</pada>
<pada selected='y'>
	<padanum>8</padanum>
	<headword>tvam</headword>
	<stem>tvad</stem>
	<morphids>x1s</morphids>
	<lexids></lexids>
	<root></root>
	<comment></comment>
</pada>
<pada selected='y'>
	<padanum>9</padanum>
	<headword>mAtula</headword>
	<stem>mAtula</stem>
	<morphids>iic</morphids>
	<lexids></lexids>
	<root></root>
	<comment></comment>
</pada>
<pada>
	<padanum>10</padanum>
	<headword>pakzam</headword>
	<stem>pakza</stem>
	<morphids>m2s</morphids>
	<lexids>ctp6</lexids>
	<root></root>
	<comment></comment>
</pada>
<pada selected='y'>
	<padanum>13</padanum>
	<headword>nASayasi</headword>
	<stem>naS_1</stem>
	<morphids>cau pre a2s</morphids>
	<lexids></lexids>
	<root></root>
	<comment></comment>
</pada>

</solution>
