<solution prefix='mbh12_' sentenceNo='26047' solutionSH='110' siftSolutions='y' status='inprogress' displayEncoding='roman' inflectionFormat='SL' version='2.0'>
	<state>1,3,13,17,19,28,30,33,34</state>
<pada selected='y'>
	<padanum>1</padanum>
	<headword>devAH</headword>
	<stem>deva</stem>
	<morphids>m1p</morphids>
	<lexids></lexids>
	<root></root>
	<comment></comment>
</pada>
<pada selected='y'>
	<padanum>3</padanum>
	<headword>tatra</headword>
	<stem>tatra</stem>
	<morphids>i</morphids>
	<lexids></lexids>
	<root></root>
	<comment></comment>
</pada>
<pada selected='y'>
	<padanum>7</padanum>
	<headword>A</headword>
	<stem>A</stem>
	<morphids>i</morphids>
	<lexids>preverb</lexids>
	<root></root>
	<comment></comment>
</pada>
<pada selected='y'>
	<padanum>7</padanum>
	<headword>agacCan</headword>
	<stem>gam</stem>
	<morphids>ipf[1] a3p</morphids>
	<lexids></lexids>
	<root></root>
	<comment></comment>
</pada>
<pada selected='y'>
	<padanum>12</padanum>
	<headword>yatra</headword>
	<stem>yatra</stem>
	<morphids>i</morphids>
	<lexids></lexids>
	<root></root>
	<comment></comment>
</pada>
<pada>
	<padanum>14</padanum>
	<headword>daDIcaH</headword>
	<stem>daDIca</stem>
	<morphids>m1s</morphids>
	<lexids>pn</lexids>
	<root></root>
	<comment></comment>
</pada>
<pada>
	<padanum>17</padanum>
	<headword>BagavAn</headword>
	<stem>Bagavat</stem>
	<morphids>m1s</morphids>
	<lexids>adj</lexids>
	<root></root>
	<comment></comment>
</pada>
<pada>
	<padanum>19</padanum>
	<headword>fziH</headword>
	<stem>fzi</stem>
	<morphids>m1s</morphids>
	<lexids>adj</lexids>
	<root></root>
	<comment></comment>
</pada>
<pada>
	<padanum>20</padanum>
	<headword>tapaH</headword>
	<stem>tapa</stem>
	<morphids>n2s</morphids>
	<lexids></lexids>
	<root></root>
	<comment></comment>
</pada>
<pada selected='y'>
	<padanum>21</padanum>
	<headword>tepe</headword>
	<stem>tap</stem>
	<morphids>prf m3s</morphids>
	<lexids></lexids>
	<root></root>
	<comment></comment>
</pada>

</solution>
