<solution prefix='mbh12_' sentenceNo='13983' solutionSH='2' siftSolutions='y' status='inprogress' displayEncoding='roman' inflectionFormat='SL' version='undefined'>
	<state>1,2,3,4,5,7,15,18,20,21,22,26,52,55,62</state>
<pada>
	<padanum>1</padanum>
	<headword>pra</headword>
	<stem>pra</stem>
	<morphids>iic</morphids>
	<lexids>preverb</lexids>
	<root></root>
	<comment></comment>
</pada>
<pada>
	<padanum>2</padanum>
	<headword>viSya</headword>
	<stem>viSya</stem>
	<morphids>i</morphids>
	<lexids>abs</lexids>
	<root>viS_1</root>
	<comment></comment>
</pada>
<pada selected='y'>
	<padanum>3</padanum>
	<headword>ca</headword>
	<stem>ca</stem>
	<morphids>i</morphids>
	<lexids></lexids>
	<root></root>
	<comment></comment>
</pada>
<pada selected='y'>
	<padanum>4</padanum>
	<headword>prARa</headword>
	<stem>prARa</stem>
	<morphids>iic</morphids>
	<lexids></lexids>
	<root></root>
	<comment></comment>
</pada>
<pada>
	<padanum>5</padanum>
	<headword>DAraRa</headword>
	<stem>DAraRa</stem>
	<morphids>iic</morphids>
	<lexids>ctp6</lexids>
	<root></root>
	<comment></comment>
</pada>
<pada selected='y'>
	<padanum>6</padanum>
	<headword>mAtrA</headword>
	<stem>mAtra</stem>
	<morphids>iic</morphids>
	<lexids></lexids>
	<root></root>
	<comment></comment>
</pada>
<pada>
	<padanum>7</padanum>
	<headword>ArTam</headword>
	<stem>ArTa</stem>
	<morphids>n2s</morphids>
	<lexids>ctp4</lexids>
	<root></root>
	<comment></comment>
</pada>
<pada>
	<padanum>8</padanum>
	<headword>dvi</headword>
	<stem>dvi</stem>
	<morphids>iic</morphids>
	<lexids></lexids>
	<root></root>
	<comment></comment>
</pada>
<pada>
	<padanum>9</padanum>
	<headword>jAtInAm</headword>
	<stem>jAti</stem>
	<morphids>m6p</morphids>
	<lexids></lexids>
	<root></root>
	<comment></comment>
</pada>
<pada>
	<padanum></padanum>
	<headword>BavanAni</headword>
	<stem>Bavana</stem>
	<morphids>n2p</morphids>
	<lexids></lexids>
	<root></root>
	<comment></comment>
</pada>
<pada>
	<padanum></padanum>
	<headword>a</headword>
	<stem>a</stem>
	<morphids>iic</morphids>
	<lexids></lexids>
	<root></root>
	<comment></comment>
</pada>
<pada>
	<padanum>14</padanum>
	<headword>saM</headword>
	<stem>sam</stem>
	<morphids>iic</morphids>
	<lexids>preverb</lexids>
	<root></root>
	<comment></comment>
</pada>
<pada>
	<padanum>15</padanum>
	<headword>kIrRa</headword>
	<stem>kIrRa</stem>
	<morphids>iic</morphids>
	<lexids>pp., ctp na</lexids>
	<root>kF</root>
	<comment></comment>
</pada>
<pada>
	<padanum>16</padanum>
	<headword>karmaRAm</headword>
	<stem>karman</stem>
	<morphids>m6p</morphids>
	<lexids>bv</lexids>
	<root></root>
	<comment></comment>
</pada>
<pada>
	<padanum>17</padanum>
	<headword>upa</headword>
	<stem>upa</stem>
	<morphids>i</morphids>
	<lexids>preverb</lexids>
	<root></root>
	<comment></comment>
</pada>
<pada selected='y'>
	<padanum>18</padanum>
	<headword>tizWeyuH</headword>
	<stem>sTA_1</stem>
	<morphids>pop[1] a3p</morphids>
	<lexids></lexids>
	<root></root>
	<comment></comment>
</pada>
<pada>
	<padanum>19</padanum>
	<headword>pAtra</headword>
	<stem>pAtra</stem>
	<morphids>iic</morphids>
	<lexids></lexids>
	<root></root>
	<comment></comment>
</pada>
<pada>
	<padanum>23</padanum>
	<headword>patita</headword>
	<stem>patita</stem>
	<morphids>iic</morphids>
	<lexids>pp., ctp2</lexids>
	<root>pat_1</root>
	<comment></comment>
</pada>
<pada>
	<padanum>38</padanum>
	<headword>a</headword>
	<stem>a</stem>
	<morphids>iic</morphids>
	<lexids></lexids>
	<root></root>
	<comment></comment>
</pada>
<pada>
	<padanum>41</padanum>
	<headword>yAcita</headword>
	<stem>yAcita</stem>
	<morphids>iic</morphids>
	<lexids>pp., ctp na</lexids>
	<root>yAc</root>
	<comment></comment>
</pada>
<pada>
	<padanum>48</padanum>
	<headword>BEkzAH</headword>
	<stem>BEkza</stem>
	<morphids>m1p</morphids>
	<lexids>ck</lexids>
	<root></root>
	<comment></comment>
</pada>
<pada>
	<padanum></padanum>
	<headword>kAma</headword>
	<stem>kAma</stem>
	<morphids>iic</morphids>
	<lexids></lexids>
	<root></root>
	<comment></comment>
</pada>
<pada>
	<padanum></padanum>
	<headword>kroDa</headword>
	<stem>kroDa</stem>
	<morphids>iic</morphids>
	<lexids>cd</lexids>
	<root></root>
	<comment></comment>
</pada>
<pada>
	<padanum></padanum>
	<headword>darpa</headword>
	<stem>darpa</stem>
	<morphids>iic</morphids>
	<lexids>cd</lexids>
	<root></root>
	<comment></comment>
</pada>
<pada>
	<padanum></padanum>
	<headword>moha</headword>
	<stem>moha</stem>
	<morphids>iic</morphids>
	<lexids>cd</lexids>
	<root></root>
	<comment></comment>
</pada>
<pada>
	<padanum></padanum>
	<headword>loBa</headword>
	<stem>loBa</stem>
	<morphids>iic</morphids>
	<lexids>cd</lexids>
	<root></root>
	<comment></comment>
</pada>
<pada>
	<padanum></padanum>
	<headword>kArpaRya</headword>
	<stem>kArpaRya</stem>
	<morphids>iic</morphids>
	<lexids>cd</lexids>
	<root></root>
	<comment></comment>
</pada>
<pada>
	<padanum></padanum>
	<headword>damBa</headword>
	<stem>damBa</stem>
	<morphids>iic</morphids>
	<lexids>cd</lexids>
	<root></root>
	<comment></comment>
</pada>
<pada>
	<padanum>49</padanum>
	<headword>parivAda</headword>
	<stem>parivAda</stem>
	<morphids>iic</morphids>
	<lexids>cd</lexids>
	<root></root>
	<comment></comment>
</pada>
<pada>
	<padanum></padanum>
	<headword>aBimAna</headword>
	<stem>aBimAna</stem>
	<morphids>iic</morphids>
	<lexids>cd</lexids>
	<root></root>
	<comment></comment>
</pada>
<pada>
	<padanum></padanum>
	<headword>hiMsA</headword>
	<stem>hiMsA</stem>
	<morphids>iic</morphids>
	<lexids>cd</lexids>
	<root></root>
	<comment></comment>
</pada>
<pada>
	<padanum></padanum>
	<headword>nivfttAH</headword>
	<stem>nivftta</stem>
	<morphids>m1p</morphids>
	<lexids>ctp6</lexids>
	<root></root>
	<comment></comment>
</pada>
<pada>
	<padanum></padanum>
	<headword>iti</headword>
	<stem>iti</stem>
	<morphids>i</morphids>
	<lexids></lexids>
	<root></root>
	<comment></comment>
</pada>

</solution>
