<solution prefix='mbh12_' sentenceNo='26149' solutionSH='0' siftSolutions='y' status='inprogress' displayEncoding='roman' inflectionFormat='SL' version='2.0'>
	<state>1,2,12,13,14,16,19</state>
<pada selected='y'>
	<padanum>1</padanum>
	<headword>aTa</headword>
	<stem>aTa</stem>
	<morphids>i</morphids>
	<lexids></lexids>
	<root></root>
	<comment></comment>
</pada>
<pada>
	<padanum></padanum>
	<headword>A</headword>
	<stem>A</stem>
	<morphids>i</morphids>
	<lexids>preverb</lexids>
	<root></root>
	<comment></comment>
</pada>
<pada>
	<padanum>2</padanum>
	<headword>agacCat</headword>
	<stem>gam</stem>
	<morphids>ipf[1] a3s</morphids>
	<lexids></lexids>
	<root></root>
	<comment></comment>
</pada>
<pada selected='y'>
	<padanum>9</padanum>
	<headword>somaH</headword>
	<stem>soma</stem>
	<morphids>m1s</morphids>
	<lexids></lexids>
	<root></root>
	<comment></comment>
</pada>
<pada selected='y'>
	<padanum>10</padanum>
	<headword>tatra</headword>
	<stem>tatra</stem>
	<morphids>i</morphids>
	<lexids></lexids>
	<root></root>
	<comment></comment>
</pada>
<pada selected='y'>
	<padanum>11</padanum>
	<headword>hiraRya</headword>
	<stem>hiraRya</stem>
	<morphids>iic</morphids>
	<lexids></lexids>
	<root></root>
	<comment></comment>
</pada>
<pada>
	<padanum>13</padanum>
	<headword>saraH</headword>
	<stem>saras</stem>
	<morphids>iic</morphids>
	<lexids>ck</lexids>
	<root></root>
	<comment></comment>
</pada>
<pada>
	<padanum>15</padanum>
	<headword>tIrTam</headword>
	<stem>tIrTa</stem>
	<morphids>n2s</morphids>
	<lexids>ck</lexids>
	<root></root>
	<comment></comment>
</pada>

</solution>
