<solution prefix='pt' sentenceNo='1049' solutionSH='168' siftSolutions='y' status='done' displayEncoding='roman' inflectionFormat='SL' version='2.0'>
	<state>1,9,11,17,40,56</state>
<pada>
	<padanum>1</padanum>
	<headword>aTa</headword>
	<stem>aTa</stem>
	<morphids>i</morphids>
	<lexids>pcl</lexids>
	<root></root>
	<comment></comment>
</pada>
<pada>
	<padanum>2</padanum>
	<headword>kadA</headword>
	<stem>kadA</stem>
	<morphids>i</morphids>
	<lexids>adv_int</lexids>
	<root></root>
	<comment></comment>
</pada>
<pada>
	<padanum>3</padanum>
	<headword>cit</headword>
	<stem>cid</stem>
	<morphids>i</morphids>
	<lexids>pcl</lexids>
	<root></root>
	<comment>making prec int indef</comment>
</pada>
<pada selected='y'>
	<padanum>4</padanum>
	<headword>jAti</headword>
	<stem>jAti</stem>
	<morphids>iic</morphids>
	<lexids></lexids>
	<root></root>
	<comment></comment>
</pada>
<pada>
	<padanum>5</padanum>
	<headword>kramAt</headword>
	<stem>krama</stem>
	<morphids>m5s</morphids>
	<lexids>noun_ctp6</lexids>
	<root></root>
	<comment></comment>
</pada>
<pada>
	<padanum>6</padanum>
	<headword>SaSakasya</headword>
	<stem>SaSaka</stem>
	<morphids>m6s</morphids>
	<lexids>noun</lexids>
	<root></root>
	<comment></comment>
</pada>
<pada>
	<padanum>7</padanum>
	<headword>avasaraH</headword>
	<stem>avasara</stem>
	<morphids>m1s</morphids>
	<lexids>noun</lexids>
	<root></root>
	<comment></comment>
</pada>
<pada>
	<padanum>8</padanum>
	<headword>sam</headword>
	<stem>sam</stem>
	<morphids>iic</morphids>
	<lexids>preverb</lexids>
	<root></root>
	<comment></comment>
</pada>
<pada>
	<padanum>9</padanum>
	<headword>jAtaH</headword>
	<stem>jAta</stem>
	<morphids>m1s</morphids>
	<lexids>ppp</lexids>
	<root>jan</root>
	<comment></comment>
</pada>

</solution>
