<solution prefix='pt' sentenceNo='1427' solutionSH='0' siftSolutions='y' status='done' displayEncoding='roman' inflectionFormat='SL' version='2.0'>
	<state>3,5,7,11,14,17,21,24,28,30,37</state>
<pada>
	<padanum>1</padanum>
	<headword>kfta</headword>
	<stem>kfta</stem>
	<morphids>iic</morphids>
	<lexids>ppp</lexids>
	<root>kf_1</root>
	<comment></comment>
</pada>
<pada selected='y'>
	<padanum>2</padanum>
	<headword>Satam</headword>
	<stem>Sata</stem>
	<morphids>n1s</morphids>
	<lexids></lexids>
	<root></root>
	<comment></comment>
</pada>
<pada selected='y'>
	<padanum>3</padanum>
	<headword>asatsu</headword>
	<stem>asat</stem>
	<morphids>m7p</morphids>
	<lexids>prap[1]</lexids>
	<root>as_2</root>
	<comment></comment>
</pada>
<pada selected='y'>
	<padanum>4</padanum>
	<headword>nazwam</headword>
	<stem>nazwa</stem>
	<morphids>n1s</morphids>
	<lexids>ppp</lexids>
	<root>naS_1</root>
	<comment></comment>
</pada>
<pada>
	<padanum>5</padanum>
	<headword>suBAzita</headword>
	<stem>suBAzita</stem>
	<morphids>iic</morphids>
	<lexids></lexids>
	<root></root>
	<comment></comment>
</pada>
<pada selected='y'>
	<padanum>6</padanum>
	<headword>Satam</headword>
	<stem>Sata</stem>
	<morphids>n1s</morphids>
	<lexids></lexids>
	<root></root>
	<comment></comment>
</pada>
<pada>
	<padanum>7</padanum>
	<headword>ca</headword>
	<stem>ca</stem>
	<morphids>i</morphids>
	<lexids></lexids>
	<root></root>
	<comment></comment>
</pada>
<pada selected='y'>
	<padanum>8</padanum>
	<headword>nazwam</headword>
	<stem>nazwa</stem>
	<morphids>n1s</morphids>
	<lexids>ppp</lexids>
	<root>naS_1</root>
	<comment></comment>
</pada>
<pada>
	<padanum>9</padanum>
	<headword>a</headword>
	<stem>a</stem>
	<morphids>iic</morphids>
	<lexids></lexids>
	<root></root>
	<comment></comment>
</pada>
<pada selected='y'>
	<padanum>10</padanum>
	<headword>buDezu</headword>
	<stem>buDa</stem>
	<morphids>m7p</morphids>
	<lexids></lexids>
	<root></root>
	<comment></comment>
</pada>
<pada>
	<padanum>11</padanum>
	<headword>vacana</headword>
	<stem>vacana</stem>
	<morphids>iic</morphids>
	<lexids></lexids>
	<root></root>
	<comment></comment>
</pada>
<pada selected='y'>
	<padanum>12</padanum>
	<headword>Satam</headword>
	<stem>Sata</stem>
	<morphids>n1s</morphids>
	<lexids></lexids>
	<root></root>
	<comment></comment>
</pada>
<pada>
	<padanum>13</padanum>
	<headword>a</headword>
	<stem>a</stem>
	<morphids>iic</morphids>
	<lexids></lexids>
	<root></root>
	<comment></comment>
</pada>
<pada>
	<padanum>14</padanum>
	<headword>vacana</headword>
	<stem>vacana</stem>
	<morphids>iic</morphids>
	<lexids></lexids>
	<root></root>
	<comment></comment>
</pada>
<pada selected='y'>
	<padanum>15</padanum>
	<headword>kare</headword>
	<stem>kara_1</stem>
	<morphids>m7s</morphids>
	<lexids></lexids>
	<root></root>
	<comment></comment>
</pada>
<pada>
	<padanum>16</padanum>
	<headword>budDi</headword>
	<stem>budDi</stem>
	<morphids>iic</morphids>
	<lexids></lexids>
	<root></root>
	<comment></comment>
</pada>
<pada selected='y'>
	<padanum>17</padanum>
	<headword>Satam</headword>
	<stem>Sata</stem>
	<morphids>n1s</morphids>
	<lexids></lexids>
	<root></root>
	<comment></comment>
</pada>
<pada>
	<padanum>18</padanum>
	<headword>a</headword>
	<stem>a</stem>
	<morphids>iic</morphids>
	<lexids></lexids>
	<root></root>
	<comment></comment>
</pada>
<pada selected='y'>
	<padanum>19</padanum>
	<headword>cetane</headword>
	<stem>cetana</stem>
	<morphids>m7s</morphids>
	<lexids></lexids>
	<root></root>
	<comment></comment>
</pada>
<pada selected='y'>
	<padanum>20</padanum>
	<headword>nazwam</headword>
	<stem>nazwa</stem>
	<morphids>n1s</morphids>
	<lexids>ppp</lexids>
	<root>naS_1</root>
	<comment></comment>
</pada>

</solution>
