<solution prefix='pt' sentenceNo='1404' solutionSH='0' siftSolutions='y' status='done' displayEncoding='roman' inflectionFormat='SL' version='2.0'>
	<state>4,6,8,12,15,20,22</state>
<pada>
	<padanum>1</padanum>
	<headword>yaH</headword>
	<stem>ya_1</stem>
	<morphids>m1s</morphids>
	<lexids></lexids>
	<root></root>
	<comment></comment>
</pada>
<pada>
	<padanum>2</padanum>
	<headword>na</headword>
	<stem>na</stem>
	<morphids>i</morphids>
	<lexids></lexids>
	<root></root>
	<comment></comment>
</pada>
<pada selected='y'>
	<padanum>3</padanum>
	<headword>niHSreyasam</headword>
	<stem>niHSreyasa</stem>
	<morphids>n2s</morphids>
	<lexids></lexids>
	<root></root>
	<comment></comment>
</pada>
<pada selected='y'>
	<padanum>4</padanum>
	<headword>jYAnam</headword>
	<stem>jYAna</stem>
	<morphids>n2s</morphids>
	<lexids></lexids>
	<root></root>
	<comment></comment>
</pada>
<pada selected='y'>
	<padanum>5</padanum>
	<headword>suhfdAm</headword>
	<stem>suhfd</stem>
	<morphids>m6p</morphids>
	<lexids></lexids>
	<root></root>
	<comment></comment>
</pada>
<pada>
	<padanum>6</padanum>
	<headword>prati</headword>
	<stem>prati</stem>
	<morphids>i</morphids>
	<lexids>preverb</lexids>
	<root></root>
	<comment></comment>
</pada>
<pada selected='y'>
	<padanum>7</padanum>
	<headword>padyate</headword>
	<stem>pad_1</stem>
	<morphids>pre[4] m3s</morphids>
	<lexids></lexids>
	<root></root>
	<comment></comment>
</pada>
<pada>
	<padanum>8</padanum>
	<headword>a</headword>
	<stem>a</stem>
	<morphids>iic</morphids>
	<lexids></lexids>
	<root></root>
	<comment></comment>
</pada>
<pada selected='y'>
	<padanum>9</padanum>
	<headword>cirAt</headword>
	<stem>cira</stem>
	<morphids>n5s</morphids>
	<lexids></lexids>
	<root></root>
	<comment></comment>
</pada>
<pada>
	<padanum>10</padanum>
	<headword>sa</headword>
	<stem>tad</stem>
	<morphids>m1s</morphids>
	<lexids></lexids>
	<root></root>
	<comment></comment>
</pada>
<pada>
	<padanum>11</padanum>
	<headword>cyutaH</headword>
	<stem>cyuta</stem>
	<morphids>m1s</morphids>
	<lexids>ppp</lexids>
	<root>cyu</root>
	<comment></comment>
</pada>
<pada>
	<padanum>12</padanum>
	<headword>sTAnAt</headword>
	<stem>sTAna</stem>
	<morphids>n5s</morphids>
	<lexids></lexids>
	<root></root>
	<comment></comment>
</pada>
<pada selected='y'>
	<padanum>13</padanum>
	<headword>dvizatAm</headword>
	<stem>dvizat</stem>
	<morphids>m6p</morphids>
	<lexids>prap[2]</lexids>
	<root>dviz_1</root>
	<comment></comment>
</pada>
<pada>
	<padanum>14</padanum>
	<headword>vartate</headword>
	<stem>vft_1</stem>
	<morphids>pre[1] m3s</morphids>
	<lexids></lexids>
	<root></root>
	<comment></comment>
</pada>
<pada selected='y'>
	<padanum>15</padanum>
	<headword>vaSe</headword>
	<stem>vaSa</stem>
	<morphids>m7s</morphids>
	<lexids></lexids>
	<root></root>
	<comment></comment>
</pada>

</solution>
