<solution prefix='pt' sentenceNo='1532' solutionSH='0' siftSolutions='y' status='done' displayEncoding='roman' inflectionFormat='SL' version='2.0'>
	<state>3</state>
<pada>
	<padanum>1</padanum>
	<headword>tataH</headword>
	<stem>tatas</stem>
	<morphids>i</morphids>
	<lexids>adv_dem</lexids>
	<root></root>
	<comment></comment>
</pada>
<pada selected='y'>
	<padanum>2</padanum>
	<headword>cintitam</headword>
	<stem>cintita</stem>
	<morphids>n1s</morphids>
	<lexids>ppp</lexids>
	<root>cint</root>
	<comment></comment>
</pada>
<pada>
	<padanum>3</padanum>
	<headword>rAjYA</headword>
	<stem>rAjan</stem>
	<morphids>m3s</morphids>
	<lexids>noun</lexids>
	<root></root>
	<comment></comment>
</pada>

</solution>
