<solution prefix='pt' sentenceNo='1783' solutionSH='0' siftSolutions='y' status='done' displayEncoding='roman' inflectionFormat='SL' version='2.0'>
	<state>2,13</state>
<pada>
	<padanum>1</padanum>
	<headword>aTa</headword>
	<stem>aTa</stem>
	<morphids>i</morphids>
	<lexids>pcl</lexids>
	<root></root>
	<comment></comment>
</pada>
<pada>
	<padanum>2</padanum>
	<headword>tasmin</headword>
	<stem>tad</stem>
	<morphids>n7s</morphids>
	<lexids>adj_dem</lexids>
	<root></root>
	<comment></comment>
</pada>
<pada>
	<padanum>3</padanum>
	<headword>eva</headword>
	<stem>eva</stem>
	<morphids>i</morphids>
	<lexids>pcl</lexids>
	<root></root>
	<comment></comment>
</pada>
<pada>
	<padanum>4</padanum>
	<headword>sarasi</headword>
	<stem>saras</stem>
	<morphids>n7s</morphids>
	<lexids>noun</lexids>
	<root></root>
	<comment></comment>
</pada>
<pada>
	<padanum>5</padanum>
	<headword>mahAn</headword>
	<stem>mahat</stem>
	<morphids>m1s</morphids>
	<lexids>adj</lexids>
	<root></root>
	<comment></comment>
</pada>
<pada>
	<padanum>6</padanum>
	<headword>vaRija</headword>
	<stem>vaRija</stem>
	<morphids>iic</morphids>
	<lexids></lexids>
	<root></root>
	<comment></comment>
</pada>
<pada>
	<padanum>7</padanum>
	<headword>ara</headword>
	<stem>ara</stem>
	<morphids>iic</morphids>
	<lexids></lexids>
	<root></root>
	<comment></comment>
</pada>
<pada>
	<padanum>8</padanum>
	<headword>ka</headword>
	<stem>ka_1</stem>
	<morphids>iic</morphids>
	<lexids></lexids>
	<root></root>
	<comment></comment>
</pada>
<pada>
	<padanum>9</padanum>
	<headword>sArTaH</headword>
	<stem>sArTa</stem>
	<morphids>m1s</morphids>
	<lexids></lexids>
	<root></root>
	<comment></comment>
</pada>
<pada>
	<padanum>10</padanum>
	<headword>A</headword>
	<stem>A</stem>
	<morphids>iic</morphids>
	<lexids>preverb</lexids>
	<root></root>
	<comment></comment>
</pada>
<pada selected='y'>
	<padanum>11</padanum>
	<headword>vAsitaH</headword>
	<stem>vAsita</stem>
	<morphids>m1s</morphids>
	<lexids>ppp_cau</lexids>
	<root>vas_1</root>
	<comment></comment>
</pada>

</solution>
