<solution prefix='pt' sentenceNo='1822' solutionSH='0' siftSolutions='y' status='done' displayEncoding='roman' inflectionFormat='SL' version='2.0'>
	<state>3</state>
<pada>
	<padanum>1</padanum>
	<headword>saH</headword>
	<stem>tad</stem>
	<morphids>m1s</morphids>
	<lexids></lexids>
	<root></root>
	<comment></comment>
</pada>
<pada>
	<padanum>2</padanum>
	<headword>uzwra</headword>
	<stem>uzwra</stem>
	<morphids>iic</morphids>
	<lexids></lexids>
	<root></root>
	<comment></comment>
</pada>
<pada selected='y'>
	<padanum>3</padanum>
	<headword>Satam</headword>
	<stem>Sata</stem>
	<morphids>n2s</morphids>
	<lexids></lexids>
	<root></root>
	<comment></comment>
</pada>
<pada>
	<padanum>4</padanum>
	<headword>bahu</headword>
	<stem>bahu</stem>
	<morphids>iic</morphids>
	<lexids></lexids>
	<root></root>
	<comment></comment>
</pada>
<pada>
	<padanum>5</padanum>
	<headword>mUlya</headword>
	<stem>mUlya</stem>
	<morphids>iic</morphids>
	<lexids></lexids>
	<root></root>
	<comment></comment>
</pada>
<pada>
	<padanum>6</padanum>
	<headword>celakasya</headword>
	<stem>celaka</stem>
	<morphids>m6s</morphids>
	<lexids></lexids>
	<root></root>
	<comment></comment>
</pada>
<pada>
	<padanum>7</padanum>
	<headword>BftvA</headword>
	<stem>Bf</stem>
	<morphids>i</morphids>
	<lexids></lexids>
	<root></root>
	<comment></comment>
</pada>
<pada>
	<padanum>8</padanum>
	<headword>kasyAMScid</headword>
	<stem>kasyAMScid</stem>
	<morphids>i</morphids>
	<lexids></lexids>
	<root></root>
	<comment></comment>
</pada>
<pada>
	<padanum>9</padanum>
	<headword>diSi</headword>
	<stem>diS_2</stem>
	<morphids>f7s</morphids>
	<lexids></lexids>
	<root></root>
	<comment></comment>
</pada>
<pada>
	<padanum>10</padanum>
	<headword>pra</headword>
	<stem>pra</stem>
	<morphids>iic</morphids>
	<lexids>preverb</lexids>
	<root></root>
	<comment></comment>
</pada>
<pada>
	<padanum>11</padanum>
	<headword>sTitaH</headword>
	<stem>sTita</stem>
	<morphids>m1s</morphids>
	<lexids>ppp</lexids>
	<root>sTA_1</root>
	<comment></comment>
</pada>

</solution>
