<solution prefix='pt' sentenceNo='1883' solutionSH='0' siftSolutions='y' status='done' displayEncoding='roman' inflectionFormat='SL' version='2.0'>
	<state>3,6</state>
<pada>
	<padanum>1</padanum>
	<headword>anyaTA</headword>
	<stem>anyaTA</stem>
	<morphids>i</morphids>
	<lexids>adv_pron</lexids>
	<root></root>
	<comment></comment>
</pada>
<pada>
	<padanum>2</padanum>
	<headword>asmAkam</headword>
	<stem>aham</stem>
	<morphids>x6p</morphids>
	<lexids>1st pron</lexids>
	<root></root>
	<comment></comment>
</pada>
<pada>
	<padanum>3</padanum>
	<headword>maDyAt</headword>
	<stem>maDya</stem>
	<morphids>m5s</morphids>
	<lexids>adj</lexids>
	<root></root>
	<comment></comment>
</pada>
<pada>
	<padanum>4</padanum>
	<headword>ekatamaH</headword>
	<stem>ekatama</stem>
	<morphids>m1s</morphids>
	<lexids>adj</lexids>
	<root></root>
	<comment></comment>
</pada>
<pada selected='y'>
	<padanum>5</padanum>
	<headword>BakzaRIyaH</headword>
	<stem>BakzaRIya</stem>
	<morphids>m1s</morphids>
	<lexids>gerundive_anIya</lexids>
	<root>Bakz</root>
	<comment></comment>
</pada>

</solution>
