<solution prefix='pt' sentenceNo='302' solutionSH='66' siftSolutions='y' status='done' displayEncoding='roman' inflectionFormat='SL' version='undefined'>
	<state>2,10,12,13,18,19,22,23,25,27,30,32,39,64,65,67</state>
<pada>
	<padanum>1</padanum>
	<headword>tat</headword>
	<stem>tad</stem>
	<morphids>m2s</morphids>
	<lexids>pron</lexids>
	<root></root>
	<comment></comment>
</pada>
<pada selected='y'>
	<padanum>2</padanum>
	<headword>na</headword>
	<stem>na</stem>
	<morphids>i</morphids>
	<lexids></lexids>
	<root></root>
	<comment></comment>
</pada>
<pada>
	<padanum>3</padanum>
	<headword>yuktam</headword>
	<stem>yukta</stem>
	<morphids>n1s</morphids>
	<lexids>noun</lexids>
	<root></root>
	<comment></comment>
</pada>
<pada selected='y'>
	<padanum>4</padanum>
	<headword>svAminaH</headword>
	<stem>svAmin</stem>
	<morphids>m6s</morphids>
	<lexids>noun</lexids>
	<root></root>
	<comment></comment>
</pada>
<pada selected='y'>
	<padanum>5</padanum>
	<headword>pUrva</headword>
	<stem>pUrva</stem>
	<morphids>iic</morphids>
	<lexids>iic</lexids>
	<root></root>
	<comment></comment>
</pada>
<pada selected='y'>
	<padanum>6</padanum>
	<headword>puruza</headword>
	<stem>puruza</stem>
	<morphids>iic</morphids>
	<lexids>iic</lexids>
	<root></root>
	<comment></comment>
</pada>
<pada selected='y'>
	<padanum>7</padanum>
	<headword>upa</headword>
	<stem>upa</stem>
	<morphids>iic</morphids>
	<lexids>preverb</lexids>
	<root></root>
	<comment></comment>
</pada>
<pada selected='y'>
	<padanum>8</padanum>
	<headword>attam</headword>
	<stem>atta</stem>
	<morphids>n2s</morphids>
	<lexids>ppp</lexids>
	<root>ad_1</root>
	<comment></comment>
</pada>
<pada selected='y'>
	<padanum>9</padanum>
	<headword>kula</headword>
	<stem>kula</stem>
	<morphids>iic</morphids>
	<lexids>iic</lexids>
	<root></root>
	<comment></comment>
</pada>
<pada selected='y'>
	<padanum>10</padanum>
	<headword>krama</headword>
	<stem>krama</stem>
	<morphids>iic</morphids>
	<lexids>iic</lexids>
	<root></root>
	<comment></comment>
</pada>
<pada selected='y'>
	<padanum>11</padanum>
	<headword>A</headword>
	<stem>A</stem>
	<morphids>iic</morphids>
	<lexids>preverb</lexids>
	<root></root>
	<comment></comment>
</pada>
<pada selected='y'>
	<padanum>12</padanum>
	<headword>gatam</headword>
	<stem>gata</stem>
	<morphids>n2s</morphids>
	<lexids>ppp</lexids>
	<root>gam</root>
	<comment></comment>
</pada>
<pada selected='y'>
	<padanum>13</padanum>
	<headword>vanam</headword>
	<stem>vana</stem>
	<morphids>n2s</morphids>
	<lexids>noun</lexids>
	<root></root>
	<comment></comment>
</pada>
<pada selected='y'>
	<padanum>14</padanum>
	<headword>eka</headword>
	<stem>eka</stem>
	<morphids>iic</morphids>
	<lexids>iic</lexids>
	<root></root>
	<comment></comment>
</pada>
<pada selected='y'>
	<padanum>15</padanum>
	<headword>pade</headword>
	<stem>pada</stem>
	<morphids>m7s</morphids>
	<lexids>noun</lexids>
	<root></root>
	<comment></comment>
</pada>
<pada selected='y'>
	<padanum>16</padanum>
	<headword>eva</headword>
	<stem>eva</stem>
	<morphids>i</morphids>
	<lexids></lexids>
	<root></root>
	<comment></comment>
</pada>
<pada selected='y'>
	<padanum>17</padanum>
	<headword>pari</headword>
	<stem>pari</stem>
	<morphids>i</morphids>
	<lexids></lexids>
	<root></root>
	<comment></comment>
</pada>
<pada selected='y'>
	<padanum>18</padanum>
	<headword>tyaktum</headword>
	<stem>tyaj_1</stem>
	<morphids>i</morphids>
	<lexids></lexids>
	<root></root>
	<comment></comment>
</pada>

</solution>
