<solution sentenceNo='-1' solutionSH='0' siftSolutions='y' status='done' displayEncoding='deva' inflectionFormat='SL' version='2.0'>
	<state>1,6</state>
<pada>
	<padanum>1</padanum>
	<headword>kadA</headword>
	<stem>kadA</stem>
	<morphids>i</morphids>
	<lexids>pcl</lexids>
	<root></root>
	<comment></comment>
</pada>
<pada>
	<padanum>2</padanum>
	<headword>cit</headword>
	<stem>cid_1</stem>
	<morphids>i</morphids>
	<lexids>pcl</lexids>
	<root></root>
	<comment></comment>
</pada>
<pada>
	<padanum>3</padanum>
	<headword>damanakaH</headword>
	<stem>damanaka</stem>
	<morphids>m1s</morphids>
	<lexids>noun</lexids>
	<root></root>
	<comment></comment>
</pada>
<pada>
	<padanum>4</padanum>
	<headword>ayam</headword>
	<stem>idam</stem>
	<morphids>m1s</morphids>
	<lexids>pron</lexids>
	<root></root>
	<comment></comment>
</pada>
<pada>
	<padanum>5</padanum>
	<headword>uBayavetanatvAt</headword>
	<stem>uBayavetanatva</stem>
	<morphids>n5s</morphids>
	<lexids>noun</lexids>
	<root></root>
	<comment></comment>
</pada>
<pada>
	<padanum>6</padanum>
	<headword>mama</headword>
	<stem>asmad</stem>
	<morphids>x6s</morphids>
	<lexids>pron</lexids>
	<root></root>
	<comment></comment>
</pada>
<pada>
	<padanum>7</padanum>
	<headword>upari</headword>
	<stem>upari</stem>
	<morphids>i</morphids>
	<lexids>pcl</lexids>
	<root></root>
	<comment></comment>
</pada>
<pada>
	<padanum>8</padanum>
	<headword>duzwaH</headword>
	<stem>duzwa</stem>
	<morphids>m1s</morphids>
	<lexids>ppp</lexids>
	<root>duz</root>
	<comment></comment>
</pada>
<pada>
	<padanum>9</padanum>
	<headword>syAt</headword>
	<stem>as</stem>
	<morphids>pop[2] a3s</morphids>
	<lexids>vi2a</lexids>
	<root></root>
	<comment></comment>
</pada>

</solution>
