<solution prefix='pt' sentenceNo='474' solutionSH='36' siftSolutions='y' status='done' displayEncoding='roman' inflectionFormat='SL' version='2.0'>
	<state>1,2,5,7,12,13,15,25,29,31,32,33,34,35,38,39,41</state>
<pada selected='y'>
	<padanum>1</padanum>
	<headword>na</headword>
	<stem>na</stem>
	<morphids>i</morphids>
	<lexids></lexids>
	<root></root>
	<comment></comment>
</pada>
<pada selected='y'>
	<padanum>2</padanum>
	<headword>pUjayati</headword>
	<stem>pUj</stem>
	<morphids>pre[10] a3s</morphids>
	<lexids></lexids>
	<root></root>
	<comment></comment>
</pada>
<pada selected='y'>
	<padanum>3</padanum>
	<headword>yaH</headword>
	<stem>ya_1</stem>
	<morphids>m1s</morphids>
	<lexids></lexids>
	<root></root>
	<comment></comment>
</pada>
<pada selected='y'>
	<padanum>4</padanum>
	<headword>garvAt</headword>
	<stem>garva</stem>
	<morphids>m5s</morphids>
	<lexids></lexids>
	<root></root>
	<comment></comment>
</pada>
<pada selected='y'>
	<padanum>5</padanum>
	<headword>yaTA</headword>
	<stem>yaTA</stem>
	<morphids>i</morphids>
	<lexids></lexids>
	<root></root>
	<comment></comment>
</pada>
<pada selected='y'>
	<padanum>6</padanum>
	<headword>Ocityam</headword>
	<stem>Ocitya</stem>
	<morphids>n2s</morphids>
	<lexids></lexids>
	<root></root>
	<comment></comment>
</pada>
<pada selected='y'>
	<padanum>7</padanum>
	<headword>nfpa</headword>
	<stem>nfpa</stem>
	<morphids>iic</morphids>
	<lexids></lexids>
	<root></root>
	<comment></comment>
</pada>
<pada selected='y'>
	<padanum>8</padanum>
	<headword>A</headword>
	<stem>A</stem>
	<morphids>iic</morphids>
	<lexids>preverb</lexids>
	<root></root>
	<comment></comment>
</pada>
<pada selected='y'>
	<padanum>9</padanum>
	<headword>SritAn</headword>
	<stem>Srita</stem>
	<morphids>m2p</morphids>
	<lexids>ppp</lexids>
	<root>Sri</root>
	<comment></comment>
</pada>
<pada selected='y'>
	<padanum>10</padanum>
	<headword>sa</headword>
	<stem>tad</stem>
	<morphids>m1s</morphids>
	<lexids></lexids>
	<root></root>
	<comment></comment>
</pada>
<pada selected='y'>
	<padanum>11</padanum>
	<headword>pra</headword>
	<stem>pra</stem>
	<morphids>i</morphids>
	<lexids>preverb</lexids>
	<root></root>
	<comment></comment>
</pada>
<pada selected='y'>
	<padanum>12</padanum>
	<headword>Apnoti</headword>
	<stem>Ap</stem>
	<morphids>pre[5] a3s</morphids>
	<lexids></lexids>
	<root></root>
	<comment></comment>
</pada>
<pada selected='y'>
	<padanum>13</padanum>
	<headword>pada</headword>
	<stem>pada</stem>
	<morphids>iic</morphids>
	<lexids></lexids>
	<root></root>
	<comment></comment>
</pada>
<pada selected='y'>
	<padanum>14</padanum>
	<headword>BraMSam</headword>
	<stem>BraMSa</stem>
	<morphids>m2s</morphids>
	<lexids></lexids>
	<root></root>
	<comment></comment>
</pada>
<pada selected='y'>
	<padanum>15</padanum>
	<headword>BU</headword>
	<stem>BU_2</stem>
	<morphids>iic</morphids>
	<lexids></lexids>
	<root></root>
	<comment></comment>
</pada>
<pada selected='y'>
	<padanum>16</padanum>
	<headword>pateH</headword>
	<stem>pati</stem>
	<morphids>m6s</morphids>
	<lexids></lexids>
	<root></root>
	<comment></comment>
</pada>
<pada>
	<padanum>17</padanum>
	<headword>dantilaH</headword>
	<stem>dantila</stem>
	<morphids>m1s</morphids>
	<lexids></lexids>
	<root></root>
	<comment></comment>
</pada>
<pada selected='y'>
	<padanum>18</padanum>
	<headword>yaTA</headword>
	<stem>yaTA</stem>
	<morphids>i</morphids>
	<lexids></lexids>
	<root></root>
	<comment></comment>
</pada>

</solution>
