<solution prefix='pt' sentenceNo='659' solutionSH='22' siftSolutions='y' status='done' displayEncoding='roman' inflectionFormat='SL' version='undefined'>
	<state>2,3,6,9,17,23,37,39</state>
<pada>
	<padanum>1</padanum>
	<headword>tat</headword>
	<stem>tad</stem>
	<morphids>n1s</morphids>
	<lexids>pron_dem</lexids>
	<root></root>
	<comment></comment>
</pada>
<pada>
	<padanum>2</padanum>
	<headword>tvayA</headword>
	<stem>yuzmad</stem>
	<morphids>x3s</morphids>
	<lexids>pron_p2</lexids>
	<root></root>
	<comment></comment>
</pada>
<pada>
	<padanum>3</padanum>
	<headword>vrata</headword>
	<stem>vrata</stem>
	<morphids>iic</morphids>
	<lexids></lexids>
	<root></root>
	<comment></comment>
</pada>
<pada>
	<padanum>4</padanum>
	<headword>grahaRAt</headword>
	<stem>grahaRa</stem>
	<morphids>n5s</morphids>
	<lexids>noun_ctp6</lexids>
	<root></root>
	<comment></comment>
</pada>
<pada>
	<padanum>5</padanum>
	<headword>UrDvam</headword>
	<stem>UrDva</stem>
	<morphids>i</morphids>
	<lexids>adv</lexids>
	<root></root>
	<comment></comment>
</pada>
<pada>
	<padanum>6</padanum>
	<headword>maWa</headword>
	<stem>maWa</stem>
	<morphids>iic</morphids>
	<lexids></lexids>
	<root></root>
	<comment></comment>
</pada>
<pada>
	<padanum>7</padanum>
	<headword>dvAre</headword>
	<stem>dvAr</stem>
	<morphids>n7s</morphids>
	<lexids>noun_ctp6</lexids>
	<root></root>
	<comment></comment>
</pada>
<pada>
	<padanum>8</padanum>
	<headword>tfRa</headword>
	<stem>tfRa</stem>
	<morphids>iic</morphids>
	<lexids></lexids>
	<root></root>
	<comment></comment>
</pada>
<pada>
	<padanum>9</padanum>
	<headword>kuwIrake</headword>
	<stem>kuwIraka</stem>
	<morphids>m7s</morphids>
	<lexids>noun_ctp6</lexids>
	<root></root>
	<comment></comment>
</pada>
<pada>
	<padanum>10</padanum>
	<headword>Sayitavyam</headword>
	<stem>Sayitavya</stem>
	<morphids>n1s</morphids>
	<lexids>gerundive</lexids>
	<root>SI_1</root>
	<comment></comment>
</pada>
<pada>
	<padanum>11</padanum>
	<headword>iti</headword>
	<stem>iti</stem>
	<morphids>i</morphids>
	<lexids>pcl</lexids>
	<root></root>
	<comment></comment>
</pada>

</solution>
