<solution prefix='pt' sentenceNo='719' solutionSH='388' siftSolutions='y' status='done' displayEncoding='roman' inflectionFormat='SL' version='undefined'>
	<state>1,2,9,11,19,20,27,29,34,42,43,46,47,48,49</state>
<pada>
	<padanum>1</padanum>
	<headword>kOlikaH</headword>
	<stem>kOlika</stem>
	<morphids>m1s</morphids>
	<lexids>noun</lexids>
	<root></root>
	<comment></comment>
</pada>
<pada>
	<padanum>2</padanum>
	<headword>tAm</headword>
	<stem>tad</stem>
	<morphids>f2s</morphids>
	<lexids>pron_dem</lexids>
	<root></root>
	<comment></comment>
</pada>
<pada>
	<padanum>3</padanum>
	<headword>palAyamAnAm</headword>
	<stem>palAyamAna</stem>
	<morphids>f2s</morphids>
	<lexids>prap</lexids>
	<root></root>
	<comment></comment>
</pada>
<pada>
	<padanum>4</padanum>
	<headword>kfta</headword>
	<stem>kf_1</stem>
	<morphids>iic</morphids>
	<lexids>ppp</lexids>
	<root></root>
	<comment></comment>
</pada>
<pada>
	<padanum>5</padanum>
	<headword>SfNgArAm</headword>
	<stem>SfNgAra</stem>
	<morphids>f2s</morphids>
	<lexids>adj_cbv</lexids>
	<root></root>
	<comment></comment>
</pada>
<pada>
	<padanum>6</padanum>
	<headword>ava</headword>
	<stem>ava</stem>
	<morphids>iic</morphids>
	<lexids>preverb</lexids>
	<root></root>
	<comment></comment>
</pada>
<pada>
	<padanum>7</padanum>
	<headword>lokya</headword>
	<stem>lok</stem>
	<morphids>i</morphids>
	<lexids>abs</lexids>
	<root></root>
	<comment></comment>
</pada>
<pada>
	<padanum>8</padanum>
	<headword>prAk</headword>
	<stem>prAk</stem>
	<morphids>i</morphids>
	<lexids>pcl</lexids>
	<root></root>
	<comment></comment>
</pada>
<pada>
	<padanum>9</padanum>
	<headword>eva</headword>
	<stem>eva</stem>
	<morphids>i</morphids>
	<lexids>pcl</lexids>
	<root></root>
	<comment></comment>
</pada>
<pada>
	<padanum>10</padanum>
	<headword>karRa</headword>
	<stem>karRa</stem>
	<morphids>iic</morphids>
	<lexids></lexids>
	<root></root>
	<comment></comment>
</pada>
<pada>
	<padanum>11</padanum>
	<headword>paramparayA</headword>
	<stem>paramparA</stem>
	<morphids>f3s</morphids>
	<lexids>noun_ctp6</lexids>
	<root></root>
	<comment></comment>
</pada>
<pada>
	<padanum>12</padanum>
	<headword>tasyAH</headword>
	<stem>tad</stem>
	<morphids>f6s</morphids>
	<lexids>pron_dem</lexids>
	<root></root>
	<comment></comment>
</pada>
<pada>
	<padanum>13</padanum>
	<headword>paravAda</headword>
	<stem>paravAda</stem>
	<morphids>iic</morphids>
	<lexids></lexids>
	<root></root>
	<comment></comment>
</pada>
<pada>
	<padanum>14</padanum>
	<headword>SravaRAt</headword>
	<stem>SravaRa_1</stem>
	<morphids>n5s</morphids>
	<lexids>noun_ctp6</lexids>
	<root></root>
	<comment></comment>
</pada>
<pada selected='y'>
	<padanum>15</padanum>
	<headword>kzuBita</headword>
	<stem>kzuBita</stem>
	<morphids>iic</morphids>
	<lexids>ppp</lexids>
	<root>kzuB</root>
	<comment></comment>
</pada>
<pada>
	<padanum>16</padanum>
	<headword>hfdayaH</headword>
	<stem>hfdaya</stem>
	<morphids>m1s</morphids>
	<lexids>adj_cbv</lexids>
	<root></root>
	<comment></comment>
</pada>
<pada>
	<padanum>17</padanum>
	<headword>kroDa</headword>
	<stem>kroDa</stem>
	<morphids>iic</morphids>
	<lexids></lexids>
	<root></root>
	<comment></comment>
</pada>
<pada>
	<padanum>18</padanum>
	<headword>vaSataH</headword>
	<stem>vaSa</stem>
	<morphids>i</morphids>
	<lexids>noun_ctp6</lexids>
	<root></root>
	<comment></comment>
</pada>
<pada>
	<padanum>19</padanum>
	<headword>gfhe</headword>
	<stem>gfha</stem>
	<morphids>n7s</morphids>
	<lexids>noun</lexids>
	<root></root>
	<comment></comment>
</pada>
<pada>
	<padanum>20</padanum>
	<headword>pra</headword>
	<stem>pra</stem>
	<morphids>iic</morphids>
	<lexids>preverb</lexids>
	<root></root>
	<comment></comment>
</pada>
<pada>
	<padanum>21</padanum>
	<headword>viSya</headword>
	<stem>viS_1</stem>
	<morphids>i</morphids>
	<lexids>abs</lexids>
	<root></root>
	<comment></comment>
</pada>
<pada>
	<padanum>22</padanum>
	<headword>tAm</headword>
	<stem>tad</stem>
	<morphids>f2s</morphids>
	<lexids>pron_dem</lexids>
	<root></root>
	<comment></comment>
</pada>
<pada>
	<padanum>23</padanum>
	<headword>uvAca</headword>
	<stem>vac</stem>
	<morphids>prf a3s</morphids>
	<lexids>vt2a</lexids>
	<root></root>
	<comment></comment>
</pada>

</solution>
