<solution prefix='pt' sentenceNo='771' solutionSH='190' siftSolutions='y' status='done' displayEncoding='roman' inflectionFormat='SL' version='undefined'>
	<state>1,5,18,22,24,33,36</state>
<pada>
	<padanum>1</padanum>
	<headword>anyaTA</headword>
	<stem>anyaTA</stem>
	<morphids>i</morphids>
	<lexids>adv</lexids>
	<root></root>
	<comment></comment>
</pada>
<pada>
	<padanum>2</padanum>
	<headword>BUyaH</headword>
	<stem>BUyas</stem>
	<morphids>i</morphids>
	<lexids>pcl</lexids>
	<root></root>
	<comment></comment>
</pada>
<pada>
	<padanum>3</padanum>
	<headword>api</headword>
	<stem>api</stem>
	<morphids>i</morphids>
	<lexids>pcl_conj</lexids>
	<root></root>
	<comment></comment>
</pada>
<pada>
	<padanum>4</padanum>
	<headword>eza</headword>
	<stem>etad</stem>
	<morphids>m1s</morphids>
	<lexids>pron_dem</lexids>
	<root></root>
	<comment></comment>
</pada>
<pada>
	<padanum>5</padanum>
	<headword>duzwataram</headword>
	<stem>duzwatara</stem>
	<morphids>m2s</morphids>
	<lexids>adj_comp</lexids>
	<root>duz</root>
	<comment></comment>
</pada>
<pada>
	<padanum>6</padanum>
	<headword>karRa</headword>
	<stem>karRa</stem>
	<morphids>iic</morphids>
	<lexids></lexids>
	<root></root>
	<comment></comment>
</pada>
<pada selected='y'>
	<padanum>7</padanum>
	<headword>Ceda</headword>
	<stem>Ceda</stem>
	<morphids>iic</morphids>
	<lexids></lexids>
	<root></root>
	<comment></comment>
</pada>
<pada selected='y'>
	<padanum>8</padanum>
	<headword>Adi</headword>
	<stem>Adi</stem>
	<morphids>iic</morphids>
	<lexids></lexids>
	<root></root>
	<comment></comment>
</pada>
<pada>
	<padanum>9</padanum>
	<headword>nigraham</headword>
	<stem>nigraha</stem>
	<morphids>m2s</morphids>
	<lexids>ctp6</lexids>
	<root></root>
	<comment></comment>
</pada>
<pada>
	<padanum>10</padanum>
	<headword>karizyati</headword>
	<stem>kf_1</stem>
	<morphids>fut a3s</morphids>
	<lexids>vt8am</lexids>
	<root></root>
	<comment></comment>
</pada>

</solution>
